lubber/__main__.py
lubber/app.py
lubber/data/gitignore.txt
lubber/data/main.lua
lubber/models/__init__.py
lubber/models/config.py
lubber/models/project.py
lubber/models/state.py
lubber/resolver/__init__.py
lubber/resolver/coop.py
lubber/resolver/types.py
lubber/utils.py
lubber-0.2.1.dist-info/LICENCE
lubber-0.2.1.dist-info/METADATA
lubber-0.2.1.dist-info/WHEEL
lubber-0.2.1.dist-info/entry_points.txt
lubber-0.2.1.dist-info/RECORD
